fear_greed_index/CNNFearAndGreedIndex.py
fear_greed_index/FearAndGreedIndicator.py
fear_greed_index/__init__.py
fear_greed_index/scrape_cnn.py
fear_greed_index-0.1.4.dist-info/WHEEL
fear_greed_index-0.1.4.dist-info/METADATA
fear_greed_index-0.1.4.dist-info/RECORD
