Metadata-Version: 2.1
Name: fear-greed-index
Version: 0.1.4
Summary: CNN Fear and Greed Index
Home-page: https://github.com/DidierRLopes/fear-greed-index
License: MIT
Author: Didier Rodrigues Lopes
Author-email: dro.lopes@campus.fct.unl.pt
Requires-Python: >=3.7
Classifier: License :: OSI Approved :: MIT License
Classifier: Programming Language :: Python :: 3
Classifier: Programming Language :: Python :: 3.10
Classifier: Programming Language :: Python :: 3.7
Classifier: Programming Language :: Python :: 3.8
Classifier: Programming Language :: Python :: 3.9
Requires-Dist: Pillow (>=9.0.0,<10.0.0)
Requires-Dist: Sphinx (>=4.0.2,<5.0.0)
Requires-Dist: bs4 (>=0.0.1,<0.0.2)
Requires-Dist: lxml (>=4.6.5,<5.0.0)
Requires-Dist: m2r2 (>=0.2.7,<0.3.0)
Requires-Dist: matplotlib (>=3.3.4,<4.0.0)
Requires-Dist: requests (>=2.25.1,<3.0.0)
Requires-Dist: sphinx-rtd-theme (>=0.5.2,<0.6.0)
Project-URL: Repository, https://github.com/DidierRLopes/fear-greed-index
